tests/integration/__init__.py
tests/integration/test_command.py
tests/unit/__init__.py
tests/unit/test_git.py
tests/unit/test_utils.py
vim_pck/__init__.py
vim_pck/ansi.py
vim_pck/cli.py
vim_pck/command.py
vim_pck/configspec.ini
vim_pck/const.py
vim_pck/git.py
vim_pck/spinner.py
vim_pck/utils.py
vim_pck-0.1.0.dist-info/DESCRIPTION.rst
vim_pck-0.1.0.dist-info/METADATA
vim_pck-0.1.0.dist-info/RECORD
vim_pck-0.1.0.dist-info/WHEEL
vim_pck-0.1.0.dist-info/entry_points.txt
vim_pck-0.1.0.dist-info/metadata.json
vim_pck-0.1.0.dist-info/top_level.txt
