Metadata-Version: 2.0
Name: vim-pck
Version: 0.1.0
Summary: command-line (n)vim package manager
Home-page: https://github.com/nicodebo/vim-pck
Author: Nicolas Débonnaire
Author-email: nico.debo@openmailbox.org
License: MIT
Keywords: vim,nvim,neovim,command-line,cli,package
Platform: UNKNOWN
Classifier: Development Status :: 4 - Beta
Classifier: Environment :: Console
Classifier: Intended Audience :: Developers
Classifier: License :: OSI Approved :: MIT License
Classifier: Operating System :: Unix
Classifier: Programming Language :: Python :: 3.6
Classifier: Topic :: Utilities
Requires-Python: >=3.6
Requires-Dist: click
Requires-Dist: configobj
